CHANGES.rst
LICENSE.txt
MANIFEST.in
README.rst
setup.py
tox.ini
simpleldap/__init__.py
simpleldap/cidict.py
simpleldap.egg-info/PKG-INFO
simpleldap.egg-info/SOURCES.txt
simpleldap.egg-info/dependency_links.txt
simpleldap.egg-info/requires.txt
simpleldap.egg-info/top_level.txt
tests/cidict.py
tests/tests.py