Metadata-Version: 1.0
Name: simpleldap
Version: 0.8
Summary: A module that makes simple LDAP usage simple.
Home-page: https://github.com/gdub/python-simpleldap
Author: Gary Wilson Jr.
Author-email: gary@thegarywilson.com
License: MIT
Keywords: ldap simple simpleldap
Platform: UNKNOWN
